bits/__init__.py
bits/appengine/__init__.py
bits/appengine/bitsdb.py
bits/appengine/config.py
bits/appengine/endpoints.py
bits/appengine/theme/__init__.py
bits/appengine/theme/templates/footer.html
bits/appengine/theme/templates/header.html
bits/appengine/theme/templates/theme.html
bits/appengine/theme/templates/topnav.html
bits/appengine/theme/templates/user.html
bits/appengine/theme/templates/users.html
bits/appengine/user.py
bits_appengine-1.3.0.dist-info/METADATA
bits_appengine-1.3.0.dist-info/WHEEL
bits_appengine-1.3.0.dist-info/RECORD
